pygdbstub/__init__.py
pygdbstub/__main__.py
pygdbstub/arch.py
pygdbstub/boards.py
pygdbstub/debug.py
pygdbstub/target/__init__.py
pygdbstub/target/microwatt.py
pygdbstub_neo-0.0.1.2.dist-info/LICENSE
pygdbstub_neo-0.0.1.2.dist-info/METADATA
pygdbstub_neo-0.0.1.2.dist-info/WHEEL
pygdbstub_neo-0.0.1.2.dist-info/top_level.txt
pygdbstub_neo-0.0.1.2.dist-info/RECORD
