Metadata-Version: 2.1
Name: pygdbstub-neo
Version: 0.0.1.2
Summary: Another GDB stub implemented in Python3
Author: Jan Vraný
Keywords: gdb,stub,python
Classifier: Intended Audience :: Developers
Classifier: License :: OSI Approved :: MIT License
Classifier: Operating System :: OS Independent
Classifier: Programming Language :: Python :: 3
Classifier: Programming Language :: Python :: 3.10
License-File: LICENSE
